{
  "0": {
    "name": "Inbox",
    "tasks": [
      {
        "taskId": 11,
        "name": "Faire les courses",
        "isDone": false
      },
      {
        "taskId": 12,
        "name": "Aller à la salle",
        "isDone": false
      },
      {
        "taskId": 13,
        "name": "Promener chien",
        "isDone": false
      },
      {
        "name": "Test post task into inbox ",
        "isDone": false,
        "taskId": "45b0f7b0-2798-11eb-b9c8-2fdd0656591b"
      },
      {
        "name": "Test post task into inbox ",
        "isDone": false,
        "taskId": "6254f7e0-2798-11eb-a75c-591b8e024315"
      }
    ]
  },
  "1": {
    "name": "Apprendre VueJS",
    "tasks": [
      {
        "taskId": 21,
        "name": "Lire doc Vue2/Vue3",
        "isDone": false
      },
      {
        "taskId": 22,
        "name": "Complete beginner path ",
        "isDone": false
      },
      {
        "taskId": 23,
        "name": "Complete intermediate path",
        "isDone": false
      },
      {
        "name": "Test post task into inbox ",
        "isDone": false,
        "taskId": "d3572cb0-2798-11eb-80f7-b9e5447c1d4f"
      }
    ]
  },
  "2": {
    "name": "Recherche d'appartement",
    "tasks": [
      {
        "taskId": 21,
        "name": "Préparer un dossier",
        "isDone": false
      },
      {
        "taskId": 22,
        "project_Id": "3",
        "name": "Appeler Century21",
        "isDone": "false"
      }
    ]
  },
  "3": {
    "name": "New test project - new modification",
    "tasks": []
  },
  "5": {
    "name": "Test post new project ",
    "tasks": []
  }
}